bitronit/__init__.py
bitronit/client.py
bitronit/exceptions.py
bitronit/utils.py
bitronit/wrappers.py
bitronit/models/address.py
bitronit/models/apikeyinfo.py
bitronit/models/asset.py
bitronit/models/cryptoexternaltransaction.py
bitronit/models/dailybalance.py
bitronit/models/fiatexternaltransaction.py
bitronit/models/iban.py
bitronit/models/market.py
bitronit/models/network.py
bitronit/models/order.py
bitronit/models/orderbook.py
bitronit/models/ordercreateresponse.py
bitronit/models/restriction.py
bitronit/models/totalbalance.py
bitronit/models/tradingpair.py
bitronit/models/transaction.py
bitronit/models/transactionsummary.py
bitronit/models/wallet.py
bitronit/models/walletaddress.py
bitronit/models/withdrawconfig.py
bitronit-1.1.1.dist-info/METADATA
bitronit-1.1.1.dist-info/WHEEL
bitronit-1.1.1.dist-info/top_level.txt
bitronit-1.1.1.dist-info/RECORD
