Metadata-Version: 2.1
Name: bitronit
Version: 1.1.1
Summary: Bitronit Python Client
Author: Bitronit
Project-URL: Source, https://github.com/Bitronit/Bitronit-Python/
Keywords: bitronit exchange api sdk rest client
Classifier: Programming Language :: Python :: 3
Classifier: Operating System :: OS Independent
Requires-Python: >=3.7
Requires-Dist: requests (>=2.28.1)
Requires-Dist: simplejson (>=3.17.6)
Requires-Dist: python-dateutil (>=2.8.2)
